enpyronments/__init__.py
enpyronments/loader.py
enpyronments/settings.py
enpyronments/utils.py
enpyronments-0.1.3.dist-info/LICENSE
enpyronments-0.1.3.dist-info/WHEEL
enpyronments-0.1.3.dist-info/METADATA
enpyronments-0.1.3.dist-info/RECORD
